CHANGELOG.txt
LICENSE.txt
MANIFEST.in
README.rst
setup.py
pushbots/__init__.py
pushbots/pushbots.py
pushbots.egg-info/PKG-INFO
pushbots.egg-info/SOURCES.txt
pushbots.egg-info/dependency_links.txt
pushbots.egg-info/requires.txt
pushbots.egg-info/top_level.txt
pushbots/examples/alias.py
pushbots/examples/analytics.py
pushbots/examples/generic.py
pushbots/examples/get_token_from_alias.py
pushbots/examples/location.py
pushbots/examples/push_batch.py
pushbots/examples/tag_untag.py
pushbots/examples/unregister.py
pushbots/tests/__init__.py
pushbots/tests/alias.py
pushbots/tests/analytics.py
pushbots/tests/badge.py
pushbots/tests/device.py
pushbots/tests/device_location.py
pushbots/tests/push.py
pushbots/tests/push_batch.py
pushbots/tests/register.py
pushbots/tests/register_batch.py
pushbots/tests/run.py
pushbots/tests/tag.py
pushbots/tests/unregister.py
pushbots/tests/untag.py