Metadata-Version: 1.1
Name: pushbots
Version: 0.0.2
Summary: REST API library for pushbots.
Home-page: https://github.com/tchar/pushbots
Author: Tilemachos Charalampous
Author-email: tilemachos.charalampous@gmail.com
License: MIT
Download-URL: https://github.com/tchar/pushbots/releases
Keywords: pushbots,push,push notifications,gcm,google cloud messaging
Platform: UNKNOWN
Classifier: Development Status :: 4 - Beta
Classifier: Intended Audience :: Developers
Classifier: Topic :: Internet :: WWW/HTTP
Classifier: Topic :: Software Development :: Libraries :: Python Modules
Classifier: License :: OSI Approved :: MIT License
Classifier: Programming Language :: Python :: 2.7
Classifier: Programming Language :: Python :: 3
